pow/__init__.py
pow/ccurl_interface.py
pow/libccurl.so
PyOTA_PoW-1.1.0.dist-info/LICENSE
PyOTA_PoW-1.1.0.dist-info/METADATA
PyOTA_PoW-1.1.0.dist-info/WHEEL
PyOTA_PoW-1.1.0.dist-info/top_level.txt
PyOTA_PoW-1.1.0.dist-info/RECORD
