Metadata-Version: 2.1
Name: PyOTA-PoW
Version: 1.1.0
Summary: Ccurl PoW Interface for PyOTA
Home-page: https://github.com/iotaledger/ccurl.interface.py
Author: Levente Pap
Author-email: levente.pap@iota.org
License: MIT
Keywords: iota,tangle,iot,internet of things,api,library,cryptocurrency,balanced ternary
Platform: UNKNOWN
Classifier: Intended Audience :: Developers
Classifier: License :: OSI Approved :: MIT License
Classifier: Programming Language :: Python :: 2.7
Classifier: Programming Language :: Python :: 3
Classifier: Programming Language :: Python :: 3.5
Classifier: Programming Language :: Python :: 3.6
Classifier: Programming Language :: Python :: 3.7
Classifier: Topic :: Software Development :: Libraries :: Python Modules
Requires-Dist: pyota
